boto_source_profile_mfa/__init__.py
boto_source_profile_mfa-0.0.11.dist-info/LICENSE
boto_source_profile_mfa-0.0.11.dist-info/METADATA
boto_source_profile_mfa-0.0.11.dist-info/WHEEL
boto_source_profile_mfa-0.0.11.dist-info/entry_points.txt
boto_source_profile_mfa-0.0.11.dist-info/top_level.txt
boto_source_profile_mfa-0.0.11.dist-info/RECORD
