Metadata-Version: 2.1
Name: boto-source-profile-mfa
Version: 0.0.11
Summary: AWS boto helper library for reusing MFA tokens in profiles with the same source profile
Home-page: https://github.com/claranet/boto-source-profile-mfa
Author: Raymond Butcher
Author-email: ray.butcher@claranet.uk
License: MIT License
Platform: UNKNOWN
Requires-Dist: boto3
Requires-Dist: botocore
